obsidian_publisher/__init__.py
obsidian_publisher/cli/__init__.py
obsidian_publisher/cli/main.py
obsidian_publisher/core/__init__.py
obsidian_publisher/core/discovery.py
obsidian_publisher/core/models.py
obsidian_publisher/core/processor.py
obsidian_publisher/core/publisher.py
obsidian_publisher/images/__init__.py
obsidian_publisher/images/optimizer.py
obsidian_publisher/transforms/__init__.py
obsidian_publisher/transforms/frontmatter.py
obsidian_publisher/transforms/links.py
obsidian_publisher/transforms/tags.py
obsidian_publisher-0.1.0.dist-info/licenses/LICENSE
obsidian_publisher-0.1.0.dist-info/METADATA
obsidian_publisher-0.1.0.dist-info/WHEEL
obsidian_publisher-0.1.0.dist-info/entry_points.txt
obsidian_publisher-0.1.0.dist-info/top_level.txt
obsidian_publisher-0.1.0.dist-info/RECORD
