Metadata-Version: 2.4
Name: obsidian-publisher
Version: 0.1.0
Summary: Publish Obsidian notes to static site generators with configurable transforms
Author: Kishore Kumar
License-Expression: MIT
Project-URL: Homepage, https://github.com/akcube/obsidian-publisher
Project-URL: Repository, https://github.com/akcube/obsidian-publisher
Project-URL: Documentation, https://github.com/akcube/obsidian-publisher#readme
Project-URL: Issues, https://github.com/akcube/obsidian-publisher/issues
Keywords: obsidian,markdown,hugo,static-site,publishing,wikilinks,zettelkasten
Classifier: Development Status :: 4 - Beta
Classifier: Environment :: Console
Classifier: Intended Audience :: Developers
Classifier: Intended Audience :: End Users/Desktop
Classifier: Operating System :: OS Independent
Classifier: Programming Language :: Python :: 3
Classifier: Programming Language :: Python :: 3.10
Classifier: Programming Language :: Python :: 3.11
Classifier: Programming Language :: Python :: 3.12
Classifier: Programming Language :: Python :: 3.13
Classifier: Topic :: Documentation
Classifier: Topic :: Internet :: WWW/HTTP :: Site Management
Classifier: Topic :: Text Processing :: Markup :: Markdown
Requires-Python: >=3.10
License-File: LICENSE
Requires-Dist: pyyaml>=6.0
Requires-Dist: inflection>=0.5.1
Requires-Dist: titlecase>=2.4
Requires-Dist: Pillow>=10.0.0
Requires-Dist: click>=8.1.0
Requires-Dist: gitpython>=3.1.0
Provides-Extra: dev
Requires-Dist: pytest>=7.0; extra == "dev"
Requires-Dist: pytest-cov>=4.0; extra == "dev"
Dynamic: license-file
